yeongnok/10th_20220706-000000.csv
yeongnok/11st_20220706-000000.csv
yeongnok/12nd_20220706-000000.csv
yeongnok/13rd_20220706-000000.csv
yeongnok/14th_20220706-000000.csv
yeongnok/15th_20220706-000000.csv
yeongnok/16th_20220706-000000.csv
yeongnok/17th_20220706-000000.csv
yeongnok/18th_20220706-000000.csv
yeongnok/19th_20220706-000000.csv
yeongnok/20th_20220706-000000.csv
yeongnok/21st_20220706-000000.csv
yeongnok/6th_20220706-000000.csv
yeongnok/7th_20220706-000000.csv
yeongnok/8th_20220706-000000.csv
yeongnok/9th_20220706-000000.csv
yeongnok/__init__.py
yeongnok/congressman.py
yeongnok/meeting.py
yeongnok/period.py
yeongnok/record.py
yeongnok/request.py
yeongnok/site.py
yeongnok/congressman_list/06_congressman_list.csv
yeongnok/congressman_list/07_congressman_list.csv
yeongnok/congressman_list/08_congressman_list.csv
yeongnok/congressman_list/09_congressman_list.csv
yeongnok/congressman_list/10_congressman_list.csv
yeongnok/congressman_list/11_congressman_list.csv
yeongnok/congressman_list/12_congressman_list.csv
yeongnok/congressman_list/13_congressman_list.csv
yeongnok/congressman_list/14_congressman_list.csv
yeongnok/congressman_list/15_congressman_list.csv
yeongnok/congressman_list/16_congressman_list.csv
yeongnok/congressman_list/17_congressman_list.csv
yeongnok/congressman_list/18_congressman_list.csv
yeongnok/congressman_list/19_congressman_list.csv
yeongnok/congressman_list/20_congressman_list.csv
yeongnok/congressman_list/21_congressman_list.csv
yeongnok/congressman_list/21_congressman_list.csv~
yeongnok/congressman_list/6th_20220706-000000.csv
yeongnok/congressman_list/7th_20220706-000000.csv
yeongnok/congressman_list/8th_20220706-000000.csv
yeongnok/congressman_list/9th_20220706-000000.csv
yeongnok/region/10_ly_data.csv
yeongnok/region/8_ly_data.csv
yeongnok/region/9_ly_data.csv
yeongnok/region/__init__.py
yeongnok/region/tw.py
yeongnok/tools/__init__.py
yeongnok/tools/analyzer.py
yeongnok/tools/downloader.py
yeongnok-0.0.28.dist-info/LICENSE
yeongnok-0.0.28.dist-info/METADATA
yeongnok-0.0.28.dist-info/WHEEL
yeongnok-0.0.28.dist-info/top_level.txt
yeongnok-0.0.28.dist-info/RECORD
