Metadata-Version: 2.1
Name: yeongnok
Version: 0.0.28
Summary: Korean National Assembly data analysis tool
Home-page: https://github.com/anzhi0708/yeongnok
Author: Anji Wong
Author-email: anzhi0708@gmail.com
Keywords: korean,congress,politics,video,assembly,VOD,korea,crawler,record
Classifier: Development Status :: 4 - Beta
Classifier: Programming Language :: Python :: 3.7
Classifier: Programming Language :: Python :: 3.8
Classifier: Programming Language :: Python :: 3.9
Classifier: Programming Language :: Python :: 3.10
Classifier: Intended Audience :: Education
Classifier: Intended Audience :: Science/Research
Classifier: Topic :: Sociology :: History
Classifier: Topic :: Sociology :: Genealogy
Classifier: Topic :: Education :: Testing
Classifier: Topic :: Scientific/Engineering :: Information Analysis
Classifier: License :: OSI Approved :: Apache Software License
Classifier: Operating System :: MacOS
Classifier: Operating System :: POSIX
Classifier: Operating System :: Unix
Classifier: Natural Language :: Korean
Requires-Python: >=3.7
License-File: LICENSE
Requires-Dist: requests
Requires-Dist: objprint
Requires-Dist: faker
Requires-Dist: wget
Requires-Dist: cryptography
